MANIFEST.in
README.rst
setup.py
django_filemanager_tjh.egg-info/PKG-INFO
django_filemanager_tjh.egg-info/SOURCES.txt
django_filemanager_tjh.egg-info/dependency_links.txt
django_filemanager_tjh.egg-info/not-zip-safe
django_filemanager_tjh.egg-info/requires.txt
django_filemanager_tjh.egg-info/top_level.txt
filemanager/__init__.py
filemanager/auth.py
filemanager/decorators.py
filemanager/fields.py
filemanager/models.py
filemanager/tests.py
filemanager/urls.py
filemanager/views.py
filemanager/static/filemanager/images/16arrow-down.png
filemanager/static/filemanager/images/16arrow-up.png
filemanager/static/filemanager/images/accept.png
filemanager/static/filemanager/images/add.png
filemanager/static/filemanager/images/application_view_icons.png
filemanager/static/filemanager/images/application_view_list.png
filemanager/static/filemanager/images/bin_closed.png
filemanager/static/filemanager/images/btnOFF.gif
filemanager/static/filemanager/images/btnON.gif
filemanager/static/filemanager/images/bullet_arrow_down.png
filemanager/static/filemanager/images/bullet_arrow_up.png
filemanager/static/filemanager/images/colSortOFF.gif
filemanager/static/filemanager/images/disk.png
filemanager/static/filemanager/images/folder_add.png
filemanager/static/filemanager/images/pencil.png
filemanager/static/filemanager/images/wait30trans.gif
filemanager/static/filemanager/images/fileicons/_Close.png
filemanager/static/filemanager/images/fileicons/_Documents.png
filemanager/static/filemanager/images/fileicons/_Favorites.png
filemanager/static/filemanager/images/fileicons/_Image.png
filemanager/static/filemanager/images/fileicons/_Movie.png
filemanager/static/filemanager/images/fileicons/_Music.png
filemanager/static/filemanager/images/fileicons/_Net.png
filemanager/static/filemanager/images/fileicons/_Open.png
filemanager/static/filemanager/images/fileicons/_ProgramFiles.png
filemanager/static/filemanager/images/fileicons/_Works.png
filemanager/static/filemanager/images/fileicons/aac.png
filemanager/static/filemanager/images/fileicons/avi.png
filemanager/static/filemanager/images/fileicons/bmp.png
filemanager/static/filemanager/images/fileicons/chm.png
filemanager/static/filemanager/images/fileicons/css.png
