Metadata-Version: 1.1
Name: django-filemanager-tjh
Version: 0.6.0
Summary: A django filemanager app
Home-page: https://bitbucket.org/tim_heap/django-filemanager
Author: Tim Heap
Author-email: tim@timheap.me
License: UNKNOWN
Platform: UNKNOWN
Classifier: Environment :: Web Environment
Classifier: Intended Audience :: Developers
Classifier: Operating System :: OS Independent
Classifier: Programming Language :: Python
Classifier: Programming Language :: Python :: 2
Classifier: Programming Language :: Python :: 3
Classifier: Framework :: Django
